<assembly
  xmlns="http://maven.apache.org/plugins/maven-assembly-plugin/assembly/1.1.2"
  xmlns:xsi="http://www.w3.org/2001/XMLSchema-instance"
  xsi:schemaLocation="http://maven.apache.org/plugins/maven-assembly-plugin/assembly/1.1.2 http://maven.apache.org/xsd/assembly-1.1.2.xsd">
  <id>bin</id>

  <formats>
    <format>dir</format>
  </formats>

  <includeBaseDirectory>false</includeBaseDirectory>

  <fileSets>
    <!-- Copy /bin & /config -->
    <fileSet>
      <directory>src/main/resources</directory>
      <outputDirectory>/</outputDirectory>
      <includes>
        <include>**/*</include>
      </includes>
      <fileMode>755</fileMode>
    </fileSet>

    <!-- Create an empty logs directory -->
    <fileSet>
      <directory>src/main/assembly</directory>
      <outputDirectory>/logs</outputDirectory>
      <excludes>
        <exclude>*</exclude>
      </excludes>
    </fileSet>
  </fileSets>

  <dependencySets>
    <dependencySet>
      <outputDirectory>/lib</outputDirectory>
      <unpack>false</unpack>
      <includes>
        <include>io.vertx.*:*:jar</include>
      </includes>
      <useProjectArtifact>false</useProjectArtifact>
    </dependencySet>
    <dependencySet>
      <outputDirectory>/lib/ext</outputDirectory>
      <unpack>false</unpack>
      <excludes>
        <exclude>io.vertx.*:*</exclude>
      </excludes>
      <scope>compile</scope>
      <useProjectArtifact>false</useProjectArtifact>
    </dependencySet>
  </dependencySets>
</assembly>
